pdfxcb/__init__.py
pdfxcb/barScan.py
pdfxcb/cue-marks.py
pdfxcb/json1.py
pdfxcb/pdf.py
pdfxcb/pdfxcb.py
pdfxcb/sandbox.py
pdfxcb-3.0.0.dist-info/LICENSE
pdfxcb-3.0.0.dist-info/METADATA
pdfxcb-3.0.0.dist-info/WHEEL
pdfxcb-3.0.0.dist-info/entry_points.txt
pdfxcb-3.0.0.dist-info/top_level.txt
pdfxcb-3.0.0.dist-info/RECORD
