Metadata-Version: 2.1
Name: pdfxcb
Version: 3.0.0
Summary: Scan PDF for barcodes and split
Home-page: https://github.com/thomp/pdfxcb3
License: UNKNOWN
Platform: UNKNOWN
Classifier: Programming Language :: Python :: 3
Classifier: License :: OSI Approved :: GNU General Public License v3 (GPLv3)
Classifier: Operating System :: OS Independent
Classifier: Development Status :: 3 - Alpha
Requires-Python: >=3.6
License-File: LICENSE
